dbt/adapters/timescaledb/__init__.py
dbt/adapters/timescaledb/__version__.py
dbt/adapters/timescaledb/impl.py
dbt/include/timescaledb/__init__.py
dbt/include/timescaledb/dbt_project.yml
dbt/include/timescaledb/macros/.gitkeep
dbt/include/timescaledb/profile_template.yml
dbt_timescaledb-0.1.0.dist-info/METADATA
dbt_timescaledb-0.1.0.dist-info/WHEEL
dbt_timescaledb-0.1.0.dist-info/RECORD
