Metadata-Version: 2.1
Name: dbt-timescaledb
Version: 0.1.0
Summary: The TimescaleDB adapter plugin for dbt
Keywords: dbt timescaledb
Author-Email: Sam Debruyn <dbt.sam@debruyn.dev>
License: MIT
Classifier: Development Status :: 1 - Planning
Classifier: License :: OSI Approved :: MIT License
Classifier: Operating System :: Microsoft :: Windows
Classifier: Operating System :: MacOS :: MacOS X
Classifier: Operating System :: POSIX :: Linux
Classifier: Programming Language :: Python :: 3.11
Project-URL: Repository, https://github.com/sdebruyn/dbt-timescaledb
Requires-Python: >=3.11
Requires-Dist: dbt-postgres~=1.7.1
